biobb_model/__init__.py
biobb_model/py.typed
biobb_model/model/__init__.py
biobb_model/model/checking_log.py
biobb_model/model/common.py
biobb_model/model/fix_altlocs.py
biobb_model/model/fix_amides.py
biobb_model/model/fix_backbone.py
biobb_model/model/fix_chirality.py
biobb_model/model/fix_pdb.py
biobb_model/model/fix_pdb_utils.py
biobb_model/model/fix_side_chain.py
biobb_model/model/fix_ssbonds.py
biobb_model/model/mutate.py
biobb_model/test/__init__.py
biobb_model-5.2.0.dist-info/licenses/LICENSE
biobb_model-5.2.0.dist-info/METADATA
biobb_model-5.2.0.dist-info/WHEEL
biobb_model-5.2.0.dist-info/entry_points.txt
biobb_model-5.2.0.dist-info/top_level.txt
biobb_model-5.2.0.dist-info/RECORD
