Metadata-Version: 2.4
Name: biobb_model
Version: 5.2.0
Summary: Biobb_model is the Biobb module collection to check and model 3d structures, create mutations or reconstruct missing atoms.
Home-page: https://github.com/bioexcel/biobb_model
Author: Biobb developers
Author-email: pau.andrio@bsc.es
Project-URL: Documentation, http://biobb-model.readthedocs.io/en/latest/
Project-URL: Bioexcel, https://bioexcel.eu/
Keywords: Bioinformatics Workflows BioExcel Compatibility
Classifier: Development Status :: 5 - Production/Stable
Classifier: Programming Language :: Python :: 3.10
Classifier: License :: OSI Approved :: Apache Software License
Classifier: Operating System :: MacOS :: MacOS X
Classifier: Operating System :: POSIX
Classifier: Operating System :: Unix
Requires-Python: >=3.10
License-File: LICENSE
Requires-Dist: biobb_common==5.2.0
Requires-Dist: biobb_structure_checking>=3.15.6
Requires-Dist: xmltodict
Dynamic: author
Dynamic: author-email
Dynamic: classifier
Dynamic: description
Dynamic: description-content-type
Dynamic: home-page
Dynamic: keywords
Dynamic: license-file
Dynamic: project-url
Dynamic: requires-dist
Dynamic: requires-python
Dynamic: summary
